pyproject.toml
PKG-INFO
setup.cfg
setup.py
pyxyz.egg-info/top_level.txt
pyxyz.egg-info/SOURCES.txt
pyxyz.egg-info/dependency_links.txt
pyxyz.egg-info/PKG-INFO
pyxyz.egg-info/requires.txt
pyxyz/pyxyz_base.pyi
pyxyz/molgraph.py
pyxyz/pyxyz_base.cpython-312-x86_64-linux-gnu.so
pyxyz/base_load.py
pyxyz/pyxyz_base.cpython-39-x86_64-linux-gnu.so
pyxyz/pyxyz_base.cpython-310-x86_64-linux-gnu.so
pyxyz/pyxyz_base.cpython-313-x86_64-linux-gnu.so
pyxyz/__init__.py
pyxyz/pyxyz_base.cpython-311-x86_64-linux-gnu.so
pyxyz/pyxyz_base.cpython-314-x86_64-linux-gnu.so
pyxyz/cpppart/cpppart.py
pyxyz/test/utils.py
pyxyz/test/aminoacid_ensemble.xyz
pyxyz/test/aminoacid_ensemble_current.xyz
pyxyz/test/crest_conformersA.xyz
pyxyz/test/aminoacid_ensemble_ref.xyz
pyxyz/test/geom_analysis.xyz
pyxyz/test/tests.py
pyxyz/test/__init__.py
pyxyz/test/aminoacid_single.xyz
pyxyz/test/hydrogen_atom.xyz
pyxyz/test/crest_conformersB.xyz
pyxyz/pyutils/utils.py
pyxyz/pyutils/moltopology.py
pyxyz/pyutils/__init__.py