Metadata-Version: 2.1
Name: pyxyz24
Version: 1.0.27
Author: Nikolai Krivoshchapov
Platform: Linux
Requires-Python: >= 3.9.0
Summary: PyXYZ – A Python Library for Conformer Ensemble Manipulation
Project-URL: Gitlab home page, https://gitlab.com/knvvv/pyxyz
Project-URL: Docs, https://knvvv.gitlab.io/pyxyz
